semanticst/SemanticST_main.py
semanticst/Semantic_graphs.py
semanticst/Semantic_layers.py
semanticst/__init__.py
semanticst/loading_batches.py
semanticst/main.py
semanticst/model.py
semanticst/preprocess.py
semanticst/utils.py
semanticst-1.1.3.dist-info/LICENSE
semanticst-1.1.3.dist-info/METADATA
semanticst-1.1.3.dist-info/WHEEL
semanticst-1.1.3.dist-info/top_level.txt
semanticst-1.1.3.dist-info/RECORD
