Metadata-Version: 2.1
Name: semanticst
Version: 1.1.3
Summary: SemanticST: Spatially informed semantic graph learning for effective clustering and integration of spatial transcriptomics
Home-page: https://github.com/roxana9/SemanticST
Author: Roxana Zahedi
Author-email: r.zahedi_nasab@unsw.edu.au
License: MIT
Classifier: Programming Language :: Python :: 3
Classifier: License :: OSI Approved :: MIT License
Classifier: Operating System :: OS Independent
Requires-Python: >=3.9
License-File: LICENSE
Requires-Dist: numpy (==1.23.4)
Requires-Dist: anndata (==0.10.9)
Requires-Dist: h5py (==3.12.1)
Requires-Dist: leidenalg (==0.10.2)
Requires-Dist: louvain (==0.8.2)
Requires-Dist: matplotlib (==3.9.2)
Requires-Dist: numba (==0.60.0)
Requires-Dist: scanpy (==1.10.3)
Requires-Dist: scikit-image (==0.24.0)
Requires-Dist: scikit-learn (==1.5.2)
Requires-Dist: scikit-misc (==0.3.1)
Requires-Dist: torch (==2.5.1)
Requires-Dist: torch-geometric (==2.6.1)
Requires-Dist: rpy2 (==3.5.11)
Requires-Dist: POT (>=0.9.5)
Requires-Dist: torchviz (==0.0.2)
